<?xml version="1.0" encoding="utf-8"?>
<TextureAtlas imagePath="fakeGF.png">
	<!-- Created with Adobe Animate version 21.0.7.42652 -->
	<!-- http://www.adobe.com/products/animate.html -->
	<SubTexture name="GF Dancing Beat instance 10000" x="0" y="0" width="700" height="635" frameX="-2" frameY="-14" frameWidth="704" frameHeight="649"/>
	<SubTexture name="GF Dancing Beat instance 10001" x="701" y="0" width="704" height="635" frameX="0" frameY="-14" frameWidth="704" frameHeight="649"/>
	<SubTexture name="GF Dancing Beat instance 10002" x="1406" y="0" width="704" height="633" frameX="0" frameY="-16" frameWidth="704" frameHeight="649"/>
	<SubTexture name="GF Dancing Beat instance 10003" x="2111" y="0" width="700" height="633" frameX="-2" frameY="-16" frameWidth="704" frameHeight="649"/>
	<SubTexture name="GF Dancing Beat instance 10004" x="2812" y="0" width="700" height="636" frameX="-2" frameY="-13" frameWidth="704" frameHeight="649"/>
	<SubTexture name="GF Dancing Beat instance 10005" x="3513" y="0" width="700" height="636" frameX="-2" frameY="-13" frameWidth="704" frameHeight="649"/>
	<SubTexture name="GF Dancing Beat instance 10006" x="4214" y="0" width="700" height="638" frameX="-2" frameY="-11" frameWidth="704" frameHeight="649"/>
	<SubTexture name="GF Dancing Beat instance 10007" x="4915" y="0" width="700" height="648" frameX="-2" frameY="-1" frameWidth="704" frameHeight="649"/>
	<SubTexture name="GF Dancing Beat instance 10008" x="4915" y="0" width="700" height="648" frameX="-2" frameY="-1" frameWidth="704" frameHeight="649"/>
	<SubTexture name="GF Dancing Beat instance 10009" x="4915" y="0" width="700" height="648" frameX="-2" frameY="-1" frameWidth="704" frameHeight="649"/>
	<SubTexture name="GF Dancing Beat instance 10010" x="5616" y="0" width="700" height="649" frameX="-2" frameY="0" frameWidth="704" frameHeight="649"/>
	<SubTexture name="GF Dancing Beat instance 10011" x="5616" y="0" width="700" height="649" frameX="-2" frameY="0" frameWidth="704" frameHeight="649"/>
	<SubTexture name="GF Dancing Beat instance 10012" x="5616" y="0" width="700" height="649" frameX="-2" frameY="0" frameWidth="704" frameHeight="649"/>
	<SubTexture name="GF Dancing Beat instance 10013" x="6317" y="0" width="700" height="648" frameX="-2" frameY="-1" frameWidth="704" frameHeight="649"/>
	<SubTexture name="GF Dancing Beat instance 10014" x="6317" y="0" width="700" height="648" frameX="-2" frameY="-1" frameWidth="704" frameHeight="649"/>
	<SubTexture name="GF Dancing Beat instance 10015" x="7018" y="0" width="700" height="637" frameX="-2" frameY="-12" frameWidth="704" frameHeight="649"/>
	<SubTexture name="GF Dancing Beat instance 10016" x="0" y="650" width="704" height="637" frameX="0" frameY="-12" frameWidth="704" frameHeight="649"/>
	<SubTexture name="GF Dancing Beat instance 10017" x="705" y="650" width="704" height="637" frameX="0" frameY="-12" frameWidth="704" frameHeight="649"/>
	<SubTexture name="GF Dancing Beat instance 10018" x="1410" y="650" width="700" height="637" frameX="-2" frameY="-12" frameWidth="704" frameHeight="649"/>
	<SubTexture name="GF Dancing Beat instance 10019" x="2111" y="650" width="700" height="638" frameX="-2" frameY="-11" frameWidth="704" frameHeight="649"/>
	<SubTexture name="GF Dancing Beat instance 10020" x="2812" y="650" width="700" height="638" frameX="-2" frameY="-11" frameWidth="704" frameHeight="649"/>
	<SubTexture name="GF Dancing Beat instance 10021" x="3513" y="650" width="700" height="639" frameX="-2" frameY="-10" frameWidth="704" frameHeight="649"/>
	<SubTexture name="GF Dancing Beat instance 10022" x="4214" y="650" width="700" height="644" frameX="-2" frameY="-5" frameWidth="704" frameHeight="649"/>
	<SubTexture name="GF Dancing Beat instance 10023" x="4214" y="650" width="700" height="644" frameX="-2" frameY="-5" frameWidth="704" frameHeight="649"/>
	<SubTexture name="GF Dancing Beat instance 10024" x="4214" y="650" width="700" height="644" frameX="-2" frameY="-5" frameWidth="704" frameHeight="649"/>
	<SubTexture name="GF Dancing Beat instance 10025" x="4915" y="650" width="700" height="643" frameX="-2" frameY="-6" frameWidth="704" frameHeight="649"/>
	<SubTexture name="GF Dancing Beat instance 10026" x="4915" y="650" width="700" height="643" frameX="-2" frameY="-6" frameWidth="704" frameHeight="649"/>
	<SubTexture name="GF Dancing Beat instance 10027" x="4915" y="650" width="700" height="643" frameX="-2" frameY="-6" frameWidth="704" frameHeight="649"/>
	<SubTexture name="GF Dancing Beat instance 10028" x="5616" y="650" width="700" height="643" frameX="-2" frameY="-6" frameWidth="704" frameHeight="649"/>
	<SubTexture name="GF Dancing Beat instance 10029" x="5616" y="650" width="700" height="643" frameX="-2" frameY="-6" frameWidth="704" frameHeight="649"/>
	<SubTexture name="GF Dancing Beat instance 10030" x="0" y="0" width="700" height="635" frameX="-2" frameY="-14" frameWidth="704" frameHeight="649"/>
	<SubTexture name="GF Dancing Beat instance 10031" x="701" y="0" width="704" height="635" frameX="0" frameY="-14" frameWidth="704" frameHeight="649"/>
	<SubTexture name="GF Dancing Beat instance 10032" x="1406" y="0" width="704" height="633" frameX="0" frameY="-16" frameWidth="704" frameHeight="649"/>
	<SubTexture name="GF Dancing Beat instance 10033" x="2111" y="0" width="700" height="633" frameX="-2" frameY="-16" frameWidth="704" frameHeight="649"/>
	<SubTexture name="GF Dancing Beat instance 10034" x="2812" y="0" width="700" height="636" frameX="-2" frameY="-13" frameWidth="704" frameHeight="649"/>
	<SubTexture name="GF Dancing Beat instance 10035" x="3513" y="0" width="700" height="636" frameX="-2" frameY="-13" frameWidth="704" frameHeight="649"/>
	<SubTexture name="GF Dancing Beat instance 10036" x="4214" y="0" width="700" height="638" frameX="-2" frameY="-11" frameWidth="704" frameHeight="649"/>
	<SubTexture name="GF Dancing Beat instance 10037" x="4915" y="0" width="700" height="648" frameX="-2" frameY="-1" frameWidth="704" frameHeight="649"/>
	<SubTexture name="GF Dancing Beat instance 10038" x="4915" y="0" width="700" height="648" frameX="-2" frameY="-1" frameWidth="704" frameHeight="649"/>
	<SubTexture name="GF Dancing Beat instance 10039" x="4915" y="0" width="700" height="648" frameX="-2" frameY="-1" frameWidth="704" frameHeight="649"/>
	<SubTexture name="GF Dancing Beat instance 10040" x="5616" y="0" width="700" height="649" frameX="-2" frameY="0" frameWidth="704" frameHeight="649"/>
	<SubTexture name="GF Dancing Beat instance 10041" x="5616" y="0" width="700" height="649" frameX="-2" frameY="0" frameWidth="704" frameHeight="649"/>
	<SubTexture name="GF Dancing Beat instance 10042" x="5616" y="0" width="700" height="649" frameX="-2" frameY="0" frameWidth="704" frameHeight="649"/>
	<SubTexture name="GF Dancing Beat instance 10043" x="6317" y="0" width="700" height="648" frameX="-2" frameY="-1" frameWidth="704" frameHeight="649"/>
	<SubTexture name="GF Dancing Beat instance 10044" x="6317" y="0" width="700" height="648" frameX="-2" frameY="-1" frameWidth="704" frameHeight="649"/>
	<SubTexture name="GF Dancing Beat instance 10045" x="7018" y="0" width="700" height="637" frameX="-2" frameY="-12" frameWidth="704" frameHeight="649"/>
	<SubTexture name="GF Dancing Beat instance 10046" x="0" y="650" width="704" height="637" frameX="0" frameY="-12" frameWidth="704" frameHeight="649"/>
	<SubTexture name="GF Dancing Beat instance 10047" x="705" y="650" width="704" height="637" frameX="0" frameY="-12" frameWidth="704" frameHeight="649"/>
	<SubTexture name="GF Dancing Beat instance 10048" x="1410" y="650" width="700" height="637" frameX="-2" frameY="-12" frameWidth="704" frameHeight="649"/>
	<SubTexture name="GF Dancing Beat instance 10049" x="2111" y="650" width="700" height="638" frameX="-2" frameY="-11" frameWidth="704" frameHeight="649"/>
	<SubTexture name="GF Dancing Beat instance 10050" x="2812" y="650" width="700" height="638" frameX="-2" frameY="-11" frameWidth="704" frameHeight="649"/>
	<SubTexture name="GF Dancing Beat instance 10051" x="3513" y="650" width="700" height="639" frameX="-2" frameY="-10" frameWidth="704" frameHeight="649"/>
	<SubTexture name="GF Dancing Beat instance 10052" x="4214" y="650" width="700" height="644" frameX="-2" frameY="-5" frameWidth="704" frameHeight="649"/>
	<SubTexture name="GF Dancing Beat instance 10053" x="4214" y="650" width="700" height="644" frameX="-2" frameY="-5" frameWidth="704" frameHeight="649"/>
	<SubTexture name="GF Dancing Beat instance 10054" x="4214" y="650" width="700" height="644" frameX="-2" frameY="-5" frameWidth="704" frameHeight="649"/>
	<SubTexture name="GF Dancing Beat instance 10055" x="4915" y="650" width="700" height="643" frameX="-2" frameY="-6" frameWidth="704" frameHeight="649"/>
	<SubTexture name="GF Dancing Beat instance 10056" x="4915" y="650" width="700" height="643" frameX="-2" frameY="-6" frameWidth="704" frameHeight="649"/>
	<SubTexture name="GF Dancing Beat instance 10057" x="4915" y="650" width="700" height="643" frameX="-2" frameY="-6" frameWidth="704" frameHeight="649"/>
	<SubTexture name="GF Dancing Beat instance 10058" x="5616" y="650" width="700" height="643" frameX="-2" frameY="-6" frameWidth="704" frameHeight="649"/>
	<SubTexture name="GF Dancing Beat instance 10059" x="5616" y="650" width="700" height="643" frameX="-2" frameY="-6" frameWidth="704" frameHeight="649"/>
	<SubTexture name="GF Dancing Beat instance 10060" x="0" y="0" width="700" height="635" frameX="-2" frameY="-14" frameWidth="704" frameHeight="649"/>
	<SubTexture name="GF Dancing Beat instance 10061" x="701" y="0" width="704" height="635" frameX="0" frameY="-14" frameWidth="704" frameHeight="649"/>
	<SubTexture name="GF Dancing Beat instance 10062" x="1406" y="0" width="704" height="633" frameX="0" frameY="-16" frameWidth="704" frameHeight="649"/>
	<SubTexture name="GF Dancing Beat instance 10063" x="2111" y="0" width="700" height="633" frameX="-2" frameY="-16" frameWidth="704" frameHeight="649"/>
	<SubTexture name="GF Dancing Beat instance 10064" x="2812" y="0" width="700" height="636" frameX="-2" frameY="-13" frameWidth="704" frameHeight="649"/>
	<SubTexture name="GF Dancing Beat instance 10065" x="3513" y="0" width="700" height="636" frameX="-2" frameY="-13" frameWidth="704" frameHeight="649"/>
	<SubTexture name="GF Dancing Beat instance 10066" x="4214" y="0" width="700" height="638" frameX="-2" frameY="-11" frameWidth="704" frameHeight="649"/>
	<SubTexture name="GF Dancing Beat instance 10067" x="4915" y="0" width="700" height="648" frameX="-2" frameY="-1" frameWidth="704" frameHeight="649"/>
	<SubTexture name="GF Dancing Beat instance 10068" x="4915" y="0" width="700" height="648" frameX="-2" frameY="-1" frameWidth="704" frameHeight="649"/>
	<SubTexture name="GF Dancing Beat instance 10069" x="4915" y="0" width="700" height="648" frameX="-2" frameY="-1" frameWidth="704" frameHeight="649"/>
	<SubTexture name="GF Dancing Beat instance 10070" x="5616" y="0" width="700" height="649" frameX="-2" frameY="0" frameWidth="704" frameHeight="649"/>
	<SubTexture name="GF Dancing Beat instance 10071" x="5616" y="0" width="700" height="649" frameX="-2" frameY="0" frameWidth="704" frameHeight="649"/>
	<SubTexture name="GF Dancing Beat instance 10072" x="5616" y="0" width="700" height="649" frameX="-2" frameY="0" frameWidth="704" frameHeight="649"/>
	<SubTexture name="GF Dancing Beat instance 10073" x="6317" y="0" width="700" height="648" frameX="-2" frameY="-1" frameWidth="704" frameHeight="649"/>
	<SubTexture name="GF Dancing Beat instance 10074" x="6317" y="0" width="700" height="648" frameX="-2" frameY="-1" frameWidth="704" frameHeight="649"/>
	<SubTexture name="GF Dancing Beat instance 10075" x="7018" y="0" width="700" height="637" frameX="-2" frameY="-12" frameWidth="704" frameHeight="649"/>
	<SubTexture name="GF Dancing Beat instance 10076" x="0" y="650" width="704" height="637" frameX="0" frameY="-12" frameWidth="704" frameHeight="649"/>
	<SubTexture name="GF Dancing Beat instance 10077" x="705" y="650" width="704" height="637" frameX="0" frameY="-12" frameWidth="704" frameHeight="649"/>
	<SubTexture name="GF Dancing Beat instance 10078" x="1410" y="650" width="700" height="637" frameX="-2" frameY="-12" frameWidth="704" frameHeight="649"/>
	<SubTexture name="GF Dancing Beat instance 10079" x="2111" y="650" width="700" height="638" frameX="-2" frameY="-11" frameWidth="704" frameHeight="649"/>
	<SubTexture name="GF Dancing Beat instance 10080" x="2812" y="650" width="700" height="638" frameX="-2" frameY="-11" frameWidth="704" frameHeight="649"/>
	<SubTexture name="GF Dancing Beat instance 10081" x="3513" y="650" width="700" height="639" frameX="-2" frameY="-10" frameWidth="704" frameHeight="649"/>
	<SubTexture name="GF Dancing Beat instance 10082" x="4214" y="650" width="700" height="644" frameX="-2" frameY="-5" frameWidth="704" frameHeight="649"/>
	<SubTexture name="GF Dancing Beat instance 10083" x="4214" y="650" width="700" height="644" frameX="-2" frameY="-5" frameWidth="704" frameHeight="649"/>
	<SubTexture name="GF Dancing Beat instance 10084" x="4214" y="650" width="700" height="644" frameX="-2" frameY="-5" frameWidth="704" frameHeight="649"/>
	<SubTexture name="GF Dancing Beat instance 10085" x="4915" y="650" width="700" height="643" frameX="-2" frameY="-6" frameWidth="704" frameHeight="649"/>
	<SubTexture name="GF Dancing Beat instance 10086" x="4915" y="650" width="700" height="643" frameX="-2" frameY="-6" frameWidth="704" frameHeight="649"/>
	<SubTexture name="GF Dancing Beat instance 10087" x="4915" y="650" width="700" height="643" frameX="-2" frameY="-6" frameWidth="704" frameHeight="649"/>
	<SubTexture name="GF Dancing Beat instance 10088" x="5616" y="650" width="700" height="643" frameX="-2" frameY="-6" frameWidth="704" frameHeight="649"/>
	<SubTexture name="GF Dancing Beat instance 10089" x="5616" y="650" width="700" height="643" frameX="-2" frameY="-6" frameWidth="704" frameHeight="649"/>
	<SubTexture name="GF Dancing Beat instance 10090" x="0" y="0" width="700" height="635" frameX="-2" frameY="-14" frameWidth="704" frameHeight="649"/>
	<SubTexture name="GF Dancing Beat instance 10091" x="701" y="0" width="704" height="635" frameX="0" frameY="-14" frameWidth="704" frameHeight="649"/>
	<SubTexture name="GF Dancing Beat instance 10092" x="1406" y="0" width="704" height="633" frameX="0" frameY="-16" frameWidth="704" frameHeight="649"/>
	<SubTexture name="GF Dancing Beat instance 10093" x="2111" y="0" width="700" height="633" frameX="-2" frameY="-16" frameWidth="704" frameHeight="649"/>
	<SubTexture name="GF Dancing Beat instance 10094" x="2812" y="0" width="700" height="636" frameX="-2" frameY="-13" frameWidth="704" frameHeight="649"/>
	<SubTexture name="GF Dancing Beat instance 10095" x="3513" y="0" width="700" height="636" frameX="-2" frameY="-13" frameWidth="704" frameHeight="649"/>
	<SubTexture name="GF Dancing Beat instance 10096" x="4214" y="0" width="700" height="638" frameX="-2" frameY="-11" frameWidth="704" frameHeight="649"/>
	<SubTexture name="GF Dancing Beat instance 10097" x="4915" y="0" width="700" height="648" frameX="-2" frameY="-1" frameWidth="704" frameHeight="649"/>
	<SubTexture name="GF Dancing Beat instance 10098" x="4915" y="0" width="700" height="648" frameX="-2" frameY="-1" frameWidth="704" frameHeight="649"/>
	<SubTexture name="GF Dancing Beat instance 10099" x="4915" y="0" width="700" height="648" frameX="-2" frameY="-1" frameWidth="704" frameHeight="649"/>
	<SubTexture name="GF Dancing Beat instance 10100" x="5616" y="0" width="700" height="649" frameX="-2" frameY="0" frameWidth="704" frameHeight="649"/>
	<SubTexture name="GF Dancing Beat instance 10101" x="5616" y="0" width="700" height="649" frameX="-2" frameY="0" frameWidth="704" frameHeight="649"/>
	<SubTexture name="GF Dancing Beat instance 10102" x="5616" y="0" width="700" height="649" frameX="-2" frameY="0" frameWidth="704" frameHeight="649"/>
	<SubTexture name="GF Dancing Beat instance 10103" x="6317" y="0" width="700" height="648" frameX="-2" frameY="-1" frameWidth="704" frameHeight="649"/>
	<SubTexture name="GF Dancing Beat instance 10104" x="6317" y="0" width="700" height="648" frameX="-2" frameY="-1" frameWidth="704" frameHeight="649"/>
	<SubTexture name="GF Dancing Beat instance 10105" x="7018" y="0" width="700" height="637" frameX="-2" frameY="-12" frameWidth="704" frameHeight="649"/>
	<SubTexture name="GF Dancing Beat instance 10106" x="0" y="650" width="704" height="637" frameX="0" frameY="-12" frameWidth="704" frameHeight="649"/>
	<SubTexture name="GF Dancing Beat instance 10107" x="705" y="650" width="704" height="637" frameX="0" frameY="-12" frameWidth="704" frameHeight="649"/>
	<SubTexture name="GF Dancing Beat instance 10108" x="1410" y="650" width="700" height="637" frameX="-2" frameY="-12" frameWidth="704" frameHeight="649"/>
	<SubTexture name="GF Dancing Beat instance 10109" x="2111" y="650" width="700" height="638" frameX="-2" frameY="-11" frameWidth="704" frameHeight="649"/>
	<SubTexture name="GF Dancing Beat instance 10110" x="2812" y="650" width="700" height="638" frameX="-2" frameY="-11" frameWidth="704" frameHeight="649"/>
	<SubTexture name="GF Dancing Beat instance 10111" x="3513" y="650" width="700" height="639" frameX="-2" frameY="-10" frameWidth="704" frameHeight="649"/>
	<SubTexture name="GF Dancing Beat instance 10112" x="4214" y="650" width="700" height="644" frameX="-2" frameY="-5" frameWidth="704" frameHeight="649"/>
	<SubTexture name="GF Dancing Beat instance 10113" x="4214" y="650" width="700" height="644" frameX="-2" frameY="-5" frameWidth="704" frameHeight="649"/>
	<SubTexture name="GF Dancing Beat instance 10114" x="4214" y="650" width="700" height="644" frameX="-2" frameY="-5" frameWidth="704" frameHeight="649"/>
	<SubTexture name="GF Dancing Beat instance 10115" x="4915" y="650" width="700" height="643" frameX="-2" frameY="-6" frameWidth="704" frameHeight="649"/>
	<SubTexture name="GF Dancing Beat instance 10116" x="4915" y="650" width="700" height="643" frameX="-2" frameY="-6" frameWidth="704" frameHeight="649"/>
	<SubTexture name="GF Dancing Beat instance 10117" x="4915" y="650" width="700" height="643" frameX="-2" frameY="-6" frameWidth="704" frameHeight="649"/>
	<SubTexture name="GF Dancing Beat instance 10118" x="5616" y="650" width="700" height="643" frameX="-2" frameY="-6" frameWidth="704" frameHeight="649"/>
	<SubTexture name="GF Dancing Beat instance 10119" x="5616" y="650" width="700" height="643" frameX="-2" frameY="-6" frameWidth="704" frameHeight="649"/>
	<SubTexture name="GF Dancing Beat instance 10120" x="0" y="0" width="700" height="635" frameX="-2" frameY="-14" frameWidth="704" frameHeight="649"/>
	<SubTexture name="GF Dancing Beat instance 10121" x="701" y="0" width="704" height="635" frameX="0" frameY="-14" frameWidth="704" frameHeight="649"/>
	<SubTexture name="GF Dancing Beat instance 10122" x="1406" y="0" width="704" height="633" frameX="0" frameY="-16" frameWidth="704" frameHeight="649"/>
	<SubTexture name="GF Dancing Beat instance 10123" x="2111" y="0" width="700" height="633" frameX="-2" frameY="-16" frameWidth="704" frameHeight="649"/>
	<SubTexture name="GF Dancing Beat instance 10124" x="2812" y="0" width="700" height="636" frameX="-2" frameY="-13" frameWidth="704" frameHeight="649"/>
	<SubTexture name="GF Dancing Beat instance 10125" x="3513" y="0" width="700" height="636" frameX="-2" frameY="-13" frameWidth="704" frameHeight="649"/>
	<SubTexture name="GF Dancing Beat instance 10126" x="4214" y="0" width="700" height="638" frameX="-2" frameY="-11" frameWidth="704" frameHeight="649"/>
	<SubTexture name="GF Dancing Beat instance 10127" x="4915" y="0" width="700" height="648" frameX="-2" frameY="-1" frameWidth="704" frameHeight="649"/>
	<SubTexture name="GF Dancing Beat instance 10128" x="4915" y="0" width="700" height="648" frameX="-2" frameY="-1" frameWidth="704" frameHeight="649"/>
	<SubTexture name="GF Dancing Beat instance 10129" x="4915" y="0" width="700" height="648" frameX="-2" frameY="-1" frameWidth="704" frameHeight="649"/>
	<SubTexture name="GF Dancing Beat instance 10130" x="5616" y="0" width="700" height="649" frameX="-2" frameY="0" frameWidth="704" frameHeight="649"/>
	<SubTexture name="GF Dancing Beat instance 10131" x="5616" y="0" width="700" height="649" frameX="-2" frameY="0" frameWidth="704" frameHeight="649"/>
	<SubTexture name="GF Dancing Beat instance 10132" x="5616" y="0" width="700" height="649" frameX="-2" frameY="0" frameWidth="704" frameHeight="649"/>
	<SubTexture name="GF Dancing Beat instance 10133" x="6317" y="0" width="700" height="648" frameX="-2" frameY="-1" frameWidth="704" frameHeight="649"/>
	<SubTexture name="GF Dancing Beat instance 10134" x="6317" y="0" width="700" height="648" frameX="-2" frameY="-1" frameWidth="704" frameHeight="649"/>
	<SubTexture name="GF Dancing Beat instance 10135" x="7018" y="0" width="700" height="637" frameX="-2" frameY="-12" frameWidth="704" frameHeight="649"/>
	<SubTexture name="GF Dancing Beat instance 10136" x="0" y="650" width="704" height="637" frameX="0" frameY="-12" frameWidth="704" frameHeight="649"/>
	<SubTexture name="GF Dancing Beat instance 10137" x="705" y="650" width="704" height="637" frameX="0" frameY="-12" frameWidth="704" frameHeight="649"/>
	<SubTexture name="GF Dancing Beat instance 10138" x="1410" y="650" width="700" height="637" frameX="-2" frameY="-12" frameWidth="704" frameHeight="649"/>
	<SubTexture name="GF Dancing Beat instance 10139" x="2111" y="650" width="700" height="638" frameX="-2" frameY="-11" frameWidth="704" frameHeight="649"/>
	<SubTexture name="GF Dancing Beat instance 10140" x="2812" y="650" width="700" height="638" frameX="-2" frameY="-11" frameWidth="704" frameHeight="649"/>
	<SubTexture name="GF Dancing Beat instance 10141" x="3513" y="650" width="700" height="639" frameX="-2" frameY="-10" frameWidth="704" frameHeight="649"/>
	<SubTexture name="GF Dancing Beat instance 10142" x="4214" y="650" width="700" height="644" frameX="-2" frameY="-5" frameWidth="704" frameHeight="649"/>
	<SubTexture name="GF Dancing Beat instance 10143" x="4214" y="650" width="700" height="644" frameX="-2" frameY="-5" frameWidth="704" frameHeight="649"/>
	<SubTexture name="GF Dancing Beat instance 10144" x="4214" y="650" width="700" height="644" frameX="-2" frameY="-5" frameWidth="704" frameHeight="649"/>
	<SubTexture name="GF Dancing Beat instance 10145" x="4915" y="650" width="700" height="643" frameX="-2" frameY="-6" frameWidth="704" frameHeight="649"/>
	<SubTexture name="GF Dancing Beat instance 10146" x="4915" y="650" width="700" height="643" frameX="-2" frameY="-6" frameWidth="704" frameHeight="649"/>
	<SubTexture name="GF Dancing Beat instance 10147" x="4915" y="650" width="700" height="643" frameX="-2" frameY="-6" frameWidth="704" frameHeight="649"/>
	<SubTexture name="GF Dancing Beat instance 10148" x="5616" y="650" width="700" height="643" frameX="-2" frameY="-6" frameWidth="704" frameHeight="649"/>
	<SubTexture name="GF Dancing Beat instance 10149" x="5616" y="650" width="700" height="643" frameX="-2" frameY="-6" frameWidth="704" frameHeight="649"/>
	<SubTexture name="GF Dancing Beat instance 10150" x="0" y="0" width="700" height="635" frameX="-2" frameY="-14" frameWidth="704" frameHeight="649"/>
	<SubTexture name="GF Dancing Beat instance 10151" x="701" y="0" width="704" height="635" frameX="0" frameY="-14" frameWidth="704" frameHeight="649"/>
	<SubTexture name="GF Dancing Beat instance 10152" x="1406" y="0" width="704" height="633" frameX="0" frameY="-16" frameWidth="704" frameHeight="649"/>
	<SubTexture name="GF Dancing Beat instance 10153" x="2111" y="0" width="700" height="633" frameX="-2" frameY="-16" frameWidth="704" frameHeight="649"/>
	<SubTexture name="GF Dancing Beat instance 10154" x="2812" y="0" width="700" height="636" frameX="-2" frameY="-13" frameWidth="704" frameHeight="649"/>
	<SubTexture name="GF Dancing Beat instance 10155" x="3513" y="0" width="700" height="636" frameX="-2" frameY="-13" frameWidth="704" frameHeight="649"/>
	<SubTexture name="GF Dancing Beat instance 10156" x="4214" y="0" width="700" height="638" frameX="-2" frameY="-11" frameWidth="704" frameHeight="649"/>
	<SubTexture name="GF Dancing Beat instance 10157" x="4915" y="0" width="700" height="648" frameX="-2" frameY="-1" frameWidth="704" frameHeight="649"/>
	<SubTexture name="GF Dancing Beat instance 10158" x="4915" y="0" width="700" height="648" frameX="-2" frameY="-1" frameWidth="704" frameHeight="649"/>
	<SubTexture name="GF Dancing Beat instance 10159" x="4915" y="0" width="700" height="648" frameX="-2" frameY="-1" frameWidth="704" frameHeight="649"/>
	<SubTexture name="GF Dancing Beat instance 10160" x="5616" y="0" width="700" height="649" frameX="-2" frameY="0" frameWidth="704" frameHeight="649"/>
	<SubTexture name="GF Dancing Beat instance 10161" x="5616" y="0" width="700" height="649" frameX="-2" frameY="0" frameWidth="704" frameHeight="649"/>
	<SubTexture name="GF Dancing Beat instance 10162" x="5616" y="0" width="700" height="649" frameX="-2" frameY="0" frameWidth="704" frameHeight="649"/>
	<SubTexture name="GF Dancing Beat instance 10163" x="6317" y="0" width="700" height="648" frameX="-2" frameY="-1" frameWidth="704" frameHeight="649"/>
	<SubTexture name="GF Dancing Beat instance 10164" x="6317" y="0" width="700" height="648" frameX="-2" frameY="-1" frameWidth="704" frameHeight="649"/>
	<SubTexture name="GF Dancing Beat instance 10165" x="6317" y="0" width="700" height="648" frameX="-2" frameY="-1" frameWidth="704" frameHeight="649"/>
	<SubTexture name="GF Dancing Beat instance 10166" x="6317" y="0" width="700" height="648" frameX="-2" frameY="-1" frameWidth="704" frameHeight="649"/>
	<SubTexture name="GF Dancing Beat instance 10167" x="6317" y="0" width="700" height="648" frameX="-2" frameY="-1" frameWidth="704" frameHeight="649"/>
	<SubTexture name="GF Dancing Beat instance 10168" x="6317" y="0" width="700" height="648" frameX="-2" frameY="-1" frameWidth="704" frameHeight="649"/>
	<SubTexture name="GF Dancing Beat instance 10169" x="6317" y="0" width="700" height="648" frameX="-2" frameY="-1" frameWidth="704" frameHeight="649"/>
	<SubTexture name="GF Dancing Beat instance 10170" x="6317" y="0" width="700" height="648" frameX="-2" frameY="-1" frameWidth="704" frameHeight="649"/>
	<SubTexture name="GF Dancing Beat instance 10171" x="6317" y="0" width="700" height="648" frameX="-2" frameY="-1" frameWidth="704" frameHeight="649"/>
	<SubTexture name="GF Dancing Beat instance 10172" x="6317" y="0" width="700" height="648" frameX="-2" frameY="-1" frameWidth="704" frameHeight="649"/>
	<SubTexture name="GF Dancing Beat instance 10173" x="6317" y="0" width="700" height="648" frameX="-2" frameY="-1" frameWidth="704" frameHeight="649"/>
	<SubTexture name="GF Dancing Beat instance 10174" x="6317" y="0" width="700" height="648" frameX="-2" frameY="-1" frameWidth="704" frameHeight="649"/>
	<SubTexture name="GF Dancing Beat instance 10175" x="6317" y="650" width="700" height="648" frameX="-2" frameY="-1" frameWidth="704" frameHeight="649"/>
	<SubTexture name="GF Dancing Beat instance 10176" x="6317" y="650" width="700" height="648" frameX="-2" frameY="-1" frameWidth="704" frameHeight="649"/>
	<SubTexture name="GF Dancing Beat instance 10177" x="7018" y="650" width="700" height="636" frameX="-2" frameY="-13" frameWidth="704" frameHeight="649"/>
	<SubTexture name="GF Dancing Beat instance 10178" x="7018" y="650" width="700" height="636" frameX="-2" frameY="-13" frameWidth="704" frameHeight="649"/>
	<SubTexture name="GF Dancing Beat instance 10179" x="0" y="1299" width="700" height="636" frameX="-2" frameY="-13" frameWidth="704" frameHeight="649"/>
	<SubTexture name="GF Dancing Beat instance 10180" x="0" y="1299" width="700" height="636" frameX="-2" frameY="-13" frameWidth="704" frameHeight="649"/>
	<SubTexture name="GF Dancing Beat instance 10181" x="0" y="1299" width="700" height="636" frameX="-2" frameY="-13" frameWidth="704" frameHeight="649"/>
	<SubTexture name="GF Dancing Beat instance 10182" x="0" y="1299" width="700" height="636" frameX="-2" frameY="-13" frameWidth="704" frameHeight="649"/>
	<SubTexture name="GF Dancing Beat instance 10183" x="0" y="1299" width="700" height="636" frameX="-2" frameY="-13" frameWidth="704" frameHeight="649"/>
	<SubTexture name="GF Dancing Beat instance 10184" x="0" y="1299" width="700" height="636" frameX="-2" frameY="-13" frameWidth="704" frameHeight="649"/>
	<SubTexture name="GF Dancing Beat instance 10185" x="0" y="1299" width="700" height="636" frameX="-2" frameY="-13" frameWidth="704" frameHeight="649"/>
	<SubTexture name="GF Dancing Beat instance 10186" x="0" y="1299" width="700" height="636" frameX="-2" frameY="-13" frameWidth="704" frameHeight="649"/>
	<SubTexture name="GF Dancing Beat instance 10187" x="0" y="1299" width="700" height="636" frameX="-2" frameY="-13" frameWidth="704" frameHeight="649"/>
	<SubTexture name="GF Dancing Beat instance 10188" x="0" y="1299" width="700" height="636" frameX="-2" frameY="-13" frameWidth="704" frameHeight="649"/>
	<SubTexture name="GF Dancing Beat instance 10189" x="0" y="1299" width="700" height="636" frameX="-2" frameY="-13" frameWidth="704" frameHeight="649"/>
	<SubTexture name="GF Dancing Beat instance 10190" x="0" y="1299" width="700" height="636" frameX="-2" frameY="-13" frameWidth="704" frameHeight="649"/>
	<SubTexture name="GF Dancing Beat instance 10191" x="0" y="1299" width="700" height="636" frameX="-2" frameY="-13" frameWidth="704" frameHeight="649"/>
	<SubTexture name="GF Dancing Beat instance 10192" x="0" y="1299" width="700" height="636" frameX="-2" frameY="-13" frameWidth="704" frameHeight="649"/>
	<SubTexture name="GF Dancing Beat instance 10193" x="0" y="1299" width="700" height="636" frameX="-2" frameY="-13" frameWidth="704" frameHeight="649"/>
	<SubTexture name="GF Dancing Beat instance 10194" x="0" y="1299" width="700" height="636" frameX="-2" frameY="-13" frameWidth="704" frameHeight="649"/>
	<SubTexture name="GF Dancing Beat instance 10195" x="0" y="1299" width="700" height="636" frameX="-2" frameY="-13" frameWidth="704" frameHeight="649"/>
	<SubTexture name="GF Dancing Beat instance 10196" x="0" y="1299" width="700" height="636" frameX="-2" frameY="-13" frameWidth="704" frameHeight="649"/>
	<SubTexture name="GF Dancing Beat instance 10197" x="0" y="1299" width="700" height="636" frameX="-2" frameY="-13" frameWidth="704" frameHeight="649"/>
	<SubTexture name="GF Dancing Beat instance 10198" x="0" y="1299" width="700" height="636" frameX="-2" frameY="-13" frameWidth="704" frameHeight="649"/>
	<SubTexture name="GF Dancing Beat instance 10199" x="0" y="1299" width="700" height="636" frameX="-2" frameY="-13" frameWidth="704" frameHeight="649"/>
	<SubTexture name="GF Dancing Beat instance 10200" x="0" y="1299" width="700" height="636" frameX="-2" frameY="-13" frameWidth="704" frameHeight="649"/>
	<SubTexture name="GF Dancing Beat instance 10201" x="0" y="1299" width="700" height="636" frameX="-2" frameY="-13" frameWidth="704" frameHeight="649"/>
	<SubTexture name="GF Dancing Beat instance 10202" x="0" y="1299" width="700" height="636" frameX="-2" frameY="-13" frameWidth="704" frameHeight="649"/>
	<SubTexture name="GF Dancing Beat instance 10203" x="0" y="1299" width="700" height="636" frameX="-2" frameY="-13" frameWidth="704" frameHeight="649"/>
	<SubTexture name="GF Dancing Beat instance 10204" x="0" y="1299" width="700" height="636" frameX="-2" frameY="-13" frameWidth="704" frameHeight="649"/>
	<SubTexture name="GF Dancing Beat instance 10205" x="0" y="1299" width="700" height="636" frameX="-2" frameY="-13" frameWidth="704" frameHeight="649"/>
	<SubTexture name="GF Dancing Beat instance 10206" x="0" y="1299" width="700" height="636" frameX="-2" frameY="-13" frameWidth="704" frameHeight="649"/>
	<SubTexture name="GF Dancing Beat instance 10207" x="0" y="1299" width="700" height="636" frameX="-2" frameY="-13" frameWidth="704" frameHeight="649"/>
	<SubTexture name="GF Dancing Beat instance 10208" x="0" y="1299" width="700" height="636" frameX="-2" frameY="-13" frameWidth="704" frameHeight="649"/>
	<SubTexture name="GF Dancing Beat instance 10209" x="0" y="1299" width="700" height="636" frameX="-2" frameY="-13" frameWidth="704" frameHeight="649"/>
	<SubTexture name="GF Dancing Beat instance 10210" x="0" y="1299" width="700" height="636" frameX="-2" frameY="-13" frameWidth="704" frameHeight="649"/>
	<SubTexture name="GF Dancing Beat instance 10211" x="0" y="1299" width="700" height="636" frameX="-2" frameY="-13" frameWidth="704" frameHeight="649"/>
	<SubTexture name="GF Dancing Beat instance 10212" x="0" y="1299" width="700" height="636" frameX="-2" frameY="-13" frameWidth="704" frameHeight="649"/>
	<SubTexture name="GF Dancing Beat instance 10213" x="0" y="1299" width="700" height="636" frameX="-2" frameY="-13" frameWidth="704" frameHeight="649"/>
	<SubTexture name="GF Dancing Beat instance 10214" x="0" y="1299" width="700" height="636" frameX="-2" frameY="-13" frameWidth="704" frameHeight="649"/>
	<SubTexture name="GF Dancing Beat instance 10215" x="0" y="1299" width="700" height="636" frameX="-2" frameY="-13" frameWidth="704" frameHeight="649"/>
	<SubTexture name="GF Dancing Beat instance 10216" x="0" y="1299" width="700" height="636" frameX="-2" frameY="-13" frameWidth="704" frameHeight="649"/>
	<SubTexture name="GF Dancing Beat instance 10217" x="0" y="1299" width="700" height="636" frameX="-2" frameY="-13" frameWidth="704" frameHeight="649"/>
	<SubTexture name="GF Dancing Beat instance 10218" x="0" y="1299" width="700" height="636" frameX="-2" frameY="-13" frameWidth="704" frameHeight="649"/>
	<SubTexture name="GF Dancing Beat instance 10219" x="0" y="1299" width="700" height="636" frameX="-2" frameY="-13" frameWidth="704" frameHeight="649"/>
	<SubTexture name="GF Dancing Beat instance 10220" x="0" y="1299" width="700" height="636" frameX="-2" frameY="-13" frameWidth="704" frameHeight="649"/>
	<SubTexture name="GF Dancing Beat instance 10221" x="0" y="1299" width="700" height="636" frameX="-2" frameY="-13" frameWidth="704" frameHeight="649"/>
	<SubTexture name="GF Dancing Beat instance 10222" x="0" y="1299" width="700" height="636" frameX="-2" frameY="-13" frameWidth="704" frameHeight="649"/>
	<SubTexture name="GF Dancing Beat instance 10223" x="0" y="1299" width="700" height="636" frameX="-2" frameY="-13" frameWidth="704" frameHeight="649"/>
	<SubTexture name="GF Dancing Beat instance 10224" x="0" y="1299" width="700" height="636" frameX="-2" frameY="-13" frameWidth="704" frameHeight="649"/>
	<SubTexture name="GF Dancing Beat instance 10225" x="0" y="1299" width="700" height="636" frameX="-2" frameY="-13" frameWidth="704" frameHeight="649"/>
	<SubTexture name="GF Dancing Beat instance 10226" x="0" y="1299" width="700" height="636" frameX="-2" frameY="-13" frameWidth="704" frameHeight="649"/>
	<SubTexture name="GF Dancing Beat instance 10227" x="0" y="1299" width="700" height="636" frameX="-2" frameY="-13" frameWidth="704" frameHeight="649"/>
	<SubTexture name="GF Dancing Beat instance 10228" x="0" y="1299" width="700" height="636" frameX="-2" frameY="-13" frameWidth="704" frameHeight="649"/>
	<SubTexture name="GF Dancing Beat instance 10229" x="0" y="1299" width="700" height="636" frameX="-2" frameY="-13" frameWidth="704" frameHeight="649"/>
	<SubTexture name="GF Dancing Beat instance 10230" x="0" y="1299" width="700" height="636" frameX="-2" frameY="-13" frameWidth="704" frameHeight="649"/>
	<SubTexture name="GF Dancing Beat instance 10231" x="0" y="1299" width="700" height="636" frameX="-2" frameY="-13" frameWidth="704" frameHeight="649"/>
	<SubTexture name="GF Dancing Beat instance 10232" x="0" y="1299" width="700" height="636" frameX="-2" frameY="-13" frameWidth="704" frameHeight="649"/>
	<SubTexture name="GF Dancing Beat instance 10233" x="0" y="1299" width="700" height="636" frameX="-2" frameY="-13" frameWidth="704" frameHeight="649"/>
	<SubTexture name="GF Dancing Beat instance 10234" x="0" y="1299" width="700" height="636" frameX="-2" frameY="-13" frameWidth="704" frameHeight="649"/>
	<SubTexture name="GF Dancing Beat instance 10235" x="0" y="1299" width="700" height="636" frameX="-2" frameY="-13" frameWidth="704" frameHeight="649"/>
	<SubTexture name="GF Dancing Beat instance 10236" x="701" y="1299" width="700" height="629" frameX="-2" frameY="-20" frameWidth="704" frameHeight="649"/>
	<SubTexture name="GF Dancing Beat instance 10237" x="701" y="1299" width="700" height="629" frameX="-2" frameY="-20" frameWidth="704" frameHeight="649"/>
	<SubTexture name="GF Dancing Beat instance 10238" x="1402" y="1299" width="700" height="629" frameX="-2" frameY="-20" frameWidth="704" frameHeight="649"/>
	<SubTexture name="GF Dancing Beat instance 10239" x="1402" y="1299" width="700" height="629" frameX="-2" frameY="-20" frameWidth="704" frameHeight="649"/>
	<SubTexture name="GF Dancing Beat instance 10240" x="2103" y="1299" width="700" height="630" frameX="-2" frameY="-19" frameWidth="704" frameHeight="649"/>
	<SubTexture name="GF Dancing Beat instance 10241" x="2103" y="1299" width="700" height="630" frameX="-2" frameY="-19" frameWidth="704" frameHeight="649"/>
	<SubTexture name="GF Dancing Beat instance 10242" x="2804" y="1299" width="700" height="631" frameX="-2" frameY="-18" frameWidth="704" frameHeight="649"/>
	<SubTexture name="GF Dancing Beat instance 10243" x="2804" y="1299" width="700" height="631" frameX="-2" frameY="-18" frameWidth="704" frameHeight="649"/>
	<SubTexture name="GF Dancing Beat instance 10244" x="2804" y="1299" width="700" height="631" frameX="-2" frameY="-18" frameWidth="704" frameHeight="649"/>
	<SubTexture name="GF Dancing Beat instance 10245" x="2804" y="1299" width="700" height="631" frameX="-2" frameY="-18" frameWidth="704" frameHeight="649"/>
	<SubTexture name="GF Dancing Beat instance 10246" x="2804" y="1299" width="700" height="631" frameX="-2" frameY="-18" frameWidth="704" frameHeight="649"/>
	<SubTexture name="GF Dancing Beat instance 10247" x="2804" y="1299" width="700" height="631" frameX="-2" frameY="-18" frameWidth="704" frameHeight="649"/>
	<SubTexture name="GF Dancing Beat instance 10248" x="2804" y="1299" width="700" height="631" frameX="-2" frameY="-18" frameWidth="704" frameHeight="649"/>
	<SubTexture name="GF Dancing Beat instance 10249" x="2804" y="1299" width="700" height="631" frameX="-2" frameY="-18" frameWidth="704" frameHeight="649"/>
	<SubTexture name="GF Dancing Beat instance 10250" x="2804" y="1299" width="700" height="631" frameX="-2" frameY="-18" frameWidth="704" frameHeight="649"/>
	<SubTexture name="GF Dancing Beat instance 10251" x="2804" y="1299" width="700" height="631" frameX="-2" frameY="-18" frameWidth="704" frameHeight="649"/>
	<SubTexture name="GF Dancing Beat instance 10252" x="2804" y="1299" width="700" height="631" frameX="-2" frameY="-18" frameWidth="704" frameHeight="649"/>
	<SubTexture name="GF Dancing Beat instance 10253" x="2804" y="1299" width="700" height="631" frameX="-2" frameY="-18" frameWidth="704" frameHeight="649"/>
	<SubTexture name="GF Dancing Beat instance 10254" x="2804" y="1299" width="700" height="631" frameX="-2" frameY="-18" frameWidth="704" frameHeight="649"/>
	<SubTexture name="GF Dancing Beat instance 10255" x="2804" y="1299" width="700" height="631" frameX="-2" frameY="-18" frameWidth="704" frameHeight="649"/>
	<SubTexture name="GF Dancing Beat instance 10256" x="2804" y="1299" width="700" height="631" frameX="-2" frameY="-18" frameWidth="704" frameHeight="649"/>
	<SubTexture name="GF Dancing Beat instance 10257" x="2804" y="1299" width="700" height="631" frameX="-2" frameY="-18" frameWidth="704" frameHeight="649"/>
	<SubTexture name="GF Dancing Beat instance 10258" x="2804" y="1299" width="700" height="631" frameX="-2" frameY="-18" frameWidth="704" frameHeight="649"/>
	<SubTexture name="GF Dancing Beat instance 10259" x="2804" y="1299" width="700" height="631" frameX="-2" frameY="-18" frameWidth="704" frameHeight="649"/>
	<SubTexture name="GF Dancing Beat instance 10260" x="2804" y="1299" width="700" height="631" frameX="-2" frameY="-18" frameWidth="704" frameHeight="649"/>
	<SubTexture name="GF Dancing Beat instance 10261" x="2804" y="1299" width="700" height="631" frameX="-2" frameY="-18" frameWidth="704" frameHeight="649"/>
	<SubTexture name="GF Dancing Beat instance 10262" x="2804" y="1299" width="700" height="631" frameX="-2" frameY="-18" frameWidth="704" frameHeight="649"/>
	<SubTexture name="GF Dancing Beat instance 10263" x="2804" y="1299" width="700" height="631" frameX="-2" frameY="-18" frameWidth="704" frameHeight="649"/>
	<SubTexture name="GF Dancing Beat instance 10264" x="2804" y="1299" width="700" height="631" frameX="-2" frameY="-18" frameWidth="704" frameHeight="649"/>
	<SubTexture name="GF Dancing Beat instance 10265" x="2804" y="1299" width="700" height="631" frameX="-2" frameY="-18" frameWidth="704" frameHeight="649"/>
	<SubTexture name="GF Dancing Beat instance 10266" x="2804" y="1299" width="700" height="631" frameX="-2" frameY="-18" frameWidth="704" frameHeight="649"/>
	<SubTexture name="GF Dancing Beat instance 10267" x="2804" y="1299" width="700" height="631" frameX="-2" frameY="-18" frameWidth="704" frameHeight="649"/>
	<SubTexture name="GF Dancing Beat instance 10268" x="2804" y="1299" width="700" height="631" frameX="-2" frameY="-18" frameWidth="704" frameHeight="649"/>
	<SubTexture name="GF Dancing Beat instance 10269" x="3505" y="1299" width="700" height="633" frameX="-2" frameY="-16" frameWidth="704" frameHeight="649"/>
	<SubTexture name="GF Dancing Beat instance 10270" x="3505" y="1299" width="700" height="633" frameX="-2" frameY="-16" frameWidth="704" frameHeight="649"/>
	<SubTexture name="GF Dancing Beat instance 10271" x="4206" y="1299" width="700" height="633" frameX="-2" frameY="-16" frameWidth="704" frameHeight="649"/>
	<SubTexture name="GF Dancing Beat instance 10272" x="4907" y="1299" width="700" height="633" frameX="-2" frameY="-16" frameWidth="704" frameHeight="649"/>
	<SubTexture name="GF Dancing Beat instance 10273" x="5608" y="1299" width="700" height="634" frameX="-2" frameY="-15" frameWidth="704" frameHeight="649"/>
	<SubTexture name="GF Dancing Beat instance 10274" x="5608" y="1299" width="700" height="634" frameX="-2" frameY="-15" frameWidth="704" frameHeight="649"/>
	<SubTexture name="GF Dancing Beat instance 10275" x="5608" y="1299" width="700" height="634" frameX="-2" frameY="-15" frameWidth="704" frameHeight="649"/>
	<SubTexture name="GF Dancing Beat instance 10276" x="5608" y="1299" width="700" height="634" frameX="-2" frameY="-15" frameWidth="704" frameHeight="649"/>
	<SubTexture name="GF Dancing Beat instance 10277" x="5608" y="1299" width="700" height="634" frameX="-2" frameY="-15" frameWidth="704" frameHeight="649"/>
	<SubTexture name="GF Dancing Beat instance 10278" x="5608" y="1299" width="700" height="634" frameX="-2" frameY="-15" frameWidth="704" frameHeight="649"/>
	<SubTexture name="GF Dancing Beat instance 10279" x="5608" y="1299" width="700" height="634" frameX="-2" frameY="-15" frameWidth="704" frameHeight="649"/>
	<SubTexture name="GF Dancing Beat instance 10280" x="5608" y="1299" width="700" height="634" frameX="-2" frameY="-15" frameWidth="704" frameHeight="649"/>
	<SubTexture name="GF Dancing Beat instance 10281" x="5608" y="1299" width="700" height="634" frameX="-2" frameY="-15" frameWidth="704" frameHeight="649"/>
	<SubTexture name="GF Dancing Beat instance 10282" x="5608" y="1299" width="700" height="634" frameX="-2" frameY="-15" frameWidth="704" frameHeight="649"/>
	<SubTexture name="GF Dancing Beat instance 10283" x="5608" y="1299" width="700" height="634" frameX="-2" frameY="-15" frameWidth="704" frameHeight="649"/>
	<SubTexture name="GF Dancing Beat instance 10284" x="5608" y="1299" width="700" height="634" frameX="-2" frameY="-15" frameWidth="704" frameHeight="649"/>
	<SubTexture name="GF Dancing Beat instance 10285" x="5608" y="1299" width="700" height="634" frameX="-2" frameY="-15" frameWidth="704" frameHeight="649"/>
	<SubTexture name="GF Dancing Beat instance 10286" x="5608" y="1299" width="700" height="634" frameX="-2" frameY="-15" frameWidth="704" frameHeight="649"/>
	<SubTexture name="GF Dancing Beat instance 10287" x="5608" y="1299" width="700" height="634" frameX="-2" frameY="-15" frameWidth="704" frameHeight="649"/>
	<SubTexture name="GF Dancing Beat instance 10288" x="5608" y="1299" width="700" height="634" frameX="-2" frameY="-15" frameWidth="704" frameHeight="649"/>
	<SubTexture name="GF Dancing Beat instance 10289" x="5608" y="1299" width="700" height="634" frameX="-2" frameY="-15" frameWidth="704" frameHeight="649"/>
	<SubTexture name="GF Dancing Beat instance 10290" x="5608" y="1299" width="700" height="634" frameX="-2" frameY="-15" frameWidth="704" frameHeight="649"/>
	<SubTexture name="GF Dancing Beat instance 10291" x="5608" y="1299" width="700" height="634" frameX="-2" frameY="-15" frameWidth="704" frameHeight="649"/>
	<SubTexture name="GF Dancing Beat instance 10292" x="5608" y="1299" width="700" height="634" frameX="-2" frameY="-15" frameWidth="704" frameHeight="649"/>
	<SubTexture name="GF Dancing Beat instance 10293" x="5608" y="1299" width="700" height="634" frameX="-2" frameY="-15" frameWidth="704" frameHeight="649"/>
	<SubTexture name="GF Dancing Beat instance 10294" x="5608" y="1299" width="700" height="634" frameX="-2" frameY="-15" frameWidth="704" frameHeight="649"/>
	<SubTexture name="GF Dancing Beat instance 10295" x="5608" y="1299" width="700" height="634" frameX="-2" frameY="-15" frameWidth="704" frameHeight="649"/>
	<SubTexture name="GF Dancing Beat instance 10296" x="5608" y="1299" width="700" height="634" frameX="-2" frameY="-15" frameWidth="704" frameHeight="649"/>
	<SubTexture name="GF Dancing Beat instance 10297" x="5608" y="1299" width="700" height="634" frameX="-2" frameY="-15" frameWidth="704" frameHeight="649"/>
	<SubTexture name="GF Dancing Beat instance 10298" x="5608" y="1299" width="700" height="634" frameX="-2" frameY="-15" frameWidth="704" frameHeight="649"/>
	<SubTexture name="GF Dancing Beat instance 10299" x="5608" y="1299" width="700" height="634" frameX="-2" frameY="-15" frameWidth="704" frameHeight="649"/>
	<SubTexture name="GF Dancing Beat instance 10300" x="5608" y="1299" width="700" height="634" frameX="-2" frameY="-15" frameWidth="704" frameHeight="649"/>
	<SubTexture name="GF Dancing Beat instance 10301" x="5608" y="1299" width="700" height="634" frameX="-2" frameY="-15" frameWidth="704" frameHeight="649"/>
	<SubTexture name="GF Dancing Beat instance 10302" x="5608" y="1299" width="700" height="634" frameX="-2" frameY="-15" frameWidth="704" frameHeight="649"/>
	<SubTexture name="GF Dancing Beat instance 10303" x="5608" y="1299" width="700" height="634" frameX="-2" frameY="-15" frameWidth="704" frameHeight="649"/>
	<SubTexture name="GF Dancing Beat instance 10304" x="5608" y="1299" width="700" height="634" frameX="-2" frameY="-15" frameWidth="704" frameHeight="649"/>
	<SubTexture name="GF Dancing Beat instance 10305" x="5608" y="1299" width="700" height="634" frameX="-2" frameY="-15" frameWidth="704" frameHeight="649"/>
	<SubTexture name="GF Dancing Beat instance 10306" x="5608" y="1299" width="700" height="634" frameX="-2" frameY="-15" frameWidth="704" frameHeight="649"/>
	<SubTexture name="GF Dancing Beat instance 10307" x="5608" y="1299" width="700" height="634" frameX="-2" frameY="-15" frameWidth="704" frameHeight="649"/>
	<SubTexture name="GF Dancing Beat instance 10308" x="5608" y="1299" width="700" height="634" frameX="-2" frameY="-15" frameWidth="704" frameHeight="649"/>
	<SubTexture name="GF Dancing Beat instance 10309" x="5608" y="1299" width="700" height="634" frameX="-2" frameY="-15" frameWidth="704" frameHeight="649"/>
</TextureAtlas>
